{
  "type": "mystia_izakaya:cooking_serializers",
  "category": "misc",
  "cooking_time": 7,
  "group": "cooked_meal",
  "ingredients": [
    {
      "item": "mystias_izakaya:ji_dan"
    },
    {
      "item": "mystias_izakaya:zhu_sun"
    },
    {
      "item": "mystias_izakaya:huang_you"
    },
    {
      "item": "mystias_izakaya:mian_fen"
    }
  ],
  "negative_tags": [
    21,
    35
  ],
  "ordinary": 2,
  "positive_tags": [
    13,
    17,
    22,
    32
  ],
  "result": {
    "count": 1,
    "id": "mystias_izakaya:ban_ni_di_ke_dan"
  }
}